{
    "2020": {
        "1": {
            "C": 16.0,
            "CB": 46.0,
            "DE": 26.0,
            "DT": 31.0,
            "LB": 76.0,
            "QB": 107.0,
            "RB": 15.0,
            "T": 98.0,
            "WR": 126.0
        },
        "2": {
            "CB": 49.0,
            "DE": 29.0,
            "DT": 23.0,
            "G": 18.0,
            "LB": 19.0,
            "QB": 40.0,
            "RB": 90.0,
            "S": 83.0,
            "T": 17.0,
            "TE": 14.0,
            "WR": 103.0
        },
        "3": {
            "C": 25.0,
            "CB": 14.0,
            "DE": 13.0,
            "DT": 48.0,
            "G": 41.0,
            "LB": 72.0,
            "RB": 33.0,
            "S": 29.0,
            "T": 33.0,
            "TE": 9.0,
            "WR": 20.0
        },
        "4": {
            "C": 17.0,
            "CB": 18.0,
            "DE": 11.0,
            "DT": 18.0,
            "G": 52.0,
            "LB": 24.0,
            "QB": 0.0,
            "RB": 16.0,
            "S": 26.0,
            "T": 12.0,
            "TE": 15.0,
            "WR": 19.0
        },
        "5": {
            "C": 4.0,
            "CB": 16.0,
            "DE": 21.0,
            "DT": 12.0,
            "G": 8.0,
            "K": 0.0,
            "LB": 12.0,
            "QB": 1.0,
            "RB": 0.0,
            "S": 4.0,
            "T": 3.0,
            "WR": 44.0
        },
        "6": {
            "C": 1.0,
            "CB": 8.0,
            "DT": 15.0,
            "G": 21.0,
            "K": 9.0,
            "LB": 9.0,
            "LS": 3.0,
            "P": 7.0,
            "QB": 2.0,
            "S": 20.0,
            "T": 37.0,
            "TE": 0.0,
            "WR": 39.0
        },
        "7": {
            "C": 0.0,
            "CB": 18.0,
            "DE": 21.0,
            "DT": 1.0,
            "G": 1.0,
            "K": 0.0,
            "LB": 33.0,
            "P": 1.0,
            "QB": 1.0,
            "RB": 5.0,
            "S": 23.0,
            "T": 1.0,
            "TE": 0.0,
            "WR": 7.0
        }
    }
}