[
    {
        "Rk": 7,
        "Player": "Brandon Browner",
        "AV": 12,
        "Round": NaN,
        "Pick": NaN,
        "DrftYr": NaN,
        "Season": 2011,
        "Age": 27,
        "Team": "SEA",
        "G": 16,
        "GS": 16,
        "AV.1": 12,
        "Pos": "RCB"
    },
    {
        "Rk": 22,
        "Player": "Brian De La Puente",
        "AV": 8,
        "Round": NaN,
        "Pick": NaN,
        "DrftYr": NaN,
        "Season": 2011,
        "Age": 26,
        "Team": "NOR",
        "G": 16,
        "GS": 12,
        "AV.1": 8,
        "Pos": "C"
    },
    {
        "Rk": 35,
        "Player": "Doug Baldwin",
        "AV": 7,
        "Round": NaN,
        "Pick": NaN,
        "DrftYr": NaN,
        "Season": 2011,
        "Age": 23,
        "Team": "SEA",
        "G": 16,
        "GS": 1,
        "AV.1": 7,
        "Pos": "WR"
    },
    {
        "Rk": 37,
        "Player": "Byron Bell",
        "AV": 7,
        "Round": NaN,
        "Pick": NaN,
        "DrftYr": NaN,
        "Season": 2011,
        "Age": 22,
        "Team": "CAR",
        "G": 16,
        "GS": 12,
        "AV.1": 7,
        "Pos": "RT"
    },
    {
        "Rk": 84,
        "Player": "Dan Bailey",
        "AV": 4,
        "Round": NaN,
        "Pick": NaN,
        "DrftYr": NaN,
        "Season": 2011,
        "Age": 23,
        "Team": "DAL",
        "G": 16,
        "GS": 0,
        "AV.1": 4,
        "Pos": "K"
    },
    {
        "Rk": 87,
        "Player": "David Caldwell",
        "AV": 4,
        "Round": NaN,
        "Pick": NaN,
        "DrftYr": NaN,
        "Season": 2011,
        "Age": 24,
        "Team": "IND",
        "G": 16,
        "GS": 13,
        "AV.1": 4,
        "Pos": "SS"
    },
    {
        "Rk": 119,
        "Player": "Andrew Hawkins",
        "AV": 3,
        "Round": NaN,
        "Pick": NaN,
        "DrftYr": NaN,
        "Season": 2011,
        "Age": 25,
        "Team": "CIN",
        "G": 13,
        "GS": 0,
        "AV.1": 3,
        "Pos": "WR"
    },
    {
        "Rk": 122,
        "Player": "Lemuel Jeanpierre",
        "AV": 3,
        "Round": NaN,
        "Pick": NaN,
        "DrftYr": NaN,
        "Season": 2011,
        "Age": 24,
        "Team": "SEA",
        "G": 16,
        "GS": 5,
        "AV.1": 3,
        "Pos": "RG"
    },
    {
        "Rk": 128,
        "Player": "Joe Reitz",
        "AV": 3,
        "Round": NaN,
        "Pick": NaN,
        "DrftYr": NaN,
        "Season": 2011,
        "Age": 26,
        "Team": "IND",
        "G": 11,
        "GS": 9,
        "AV.1": 3,
        "Pos": "LG"
    },
    {
        "Rk": 129,
        "Player": "Kevin Rutland",
        "AV": 3,
        "Round": NaN,
        "Pick": NaN,
        "DrftYr": NaN,
        "Season": 2011,
        "Age": 23,
        "Team": "JAX",
        "G": 14,
        "GS": 4,
        "AV.1": 3,
        "Pos": "DB"
    },
    {
        "Rk": 144,
        "Player": "Bryan Braman",
        "AV": 2,
        "Round": NaN,
        "Pick": NaN,
        "DrftYr": NaN,
        "Season": 2011,
        "Age": 24,
        "Team": "HOU",
        "G": 16,
        "GS": 0,
        "AV.1": 2,
        "Pos": "LB"
    },
    {
        "Rk": 167,
        "Player": "Chris Harris Jr.",
        "AV": 2,
        "Round": NaN,
        "Pick": NaN,
        "DrftYr": NaN,
        "Season": 2011,
        "Age": 22,
        "Team": "DEN",
        "G": 16,
        "GS": 4,
        "AV.1": 2,
        "Pos": "DB"
    },
    {
        "Rk": 168,
        "Player": "Brett Hartmann",
        "AV": 2,
        "Round": NaN,
        "Pick": NaN,
        "DrftYr": NaN,
        "Season": 2011,
        "Age": 24,
        "Team": "HOU",
        "G": 12,
        "GS": 0,
        "AV.1": 2,
        "Pos": "P"
    },
    {
        "Rk": 169,
        "Player": "Kellen Heard",
        "AV": 2,
        "Round": NaN,
        "Pick": NaN,
        "DrftYr": NaN,
        "Season": 2011,
        "Age": 26,
        "Team": "BUF",
        "G": 15,
        "GS": 2,
        "AV.1": 2,
        "Pos": "DT"
    },
    {
        "Rk": 180,
        "Player": "Joe Lefeged",
        "AV": 2,
        "Round": NaN,
        "Pick": NaN,
        "DrftYr": NaN,
        "Season": 2011,
        "Age": 23,
        "Team": "IND",
        "G": 16,
        "GS": 1,
        "AV.1": 2,
        "Pos": "DB"
    },
    {
        "Rk": 189,
        "Player": "Albert McClellan",
        "AV": 2,
        "Round": NaN,
        "Pick": NaN,
        "DrftYr": NaN,
        "Season": 2011,
        "Age": 25,
        "Team": "BAL",
        "G": 16,
        "GS": 1,
        "AV.1": 2,
        "Pos": "LB"
    },
    {
        "Rk": 191,
        "Player": "Garrett McIntyre",
        "AV": 2,
        "Round": NaN,
        "Pick": NaN,
        "DrftYr": NaN,
        "Season": 2011,
        "Age": 27,
        "Team": "NYJ",
        "G": 13,
        "GS": 3,
        "AV.1": 2,
        "Pos": "LB"
    },
    {
        "Rk": 194,
        "Player": "Sterling Moore",
        "AV": 2,
        "Round": NaN,
        "Pick": NaN,
        "DrftYr": NaN,
        "Season": 2011,
        "Age": 21,
        "Team": "NWE",
        "G": 6,
        "GS": 3,
        "AV.1": 2,
        "Pos": "DB"
    },
    {
        "Rk": 207,
        "Player": "Dane Sanzenbacher",
        "AV": 2,
        "Round": NaN,
        "Pick": NaN,
        "DrftYr": NaN,
        "Season": 2011,
        "Age": 23,
        "Team": "CHI",
        "G": 16,
        "GS": 1,
        "AV.1": 2,
        "Pos": "WR"
    },
    {
        "Rk": 210,
        "Player": "Emmanuel Stephens",
        "AV": 2,
        "Round": NaN,
        "Pick": NaN,
        "DrftYr": NaN,
        "Season": 2011,
        "Age": 24,
        "Team": "CLE",
        "G": 11,
        "GS": 3,
        "AV.1": 2,
        "Pos": "DE"
    },
    {
        "Rk": 211,
        "Player": "Mike Tepper",
        "AV": 2,
        "Round": NaN,
        "Pick": NaN,
        "DrftYr": NaN,
        "Season": 2011,
        "Age": 26,
        "Team": "IND",
        "G": 6,
        "GS": 4,
        "AV.1": 2,
        "Pos": "T"
    },
    {
        "Rk": 221,
        "Player": "Isa Abdul-Quddus",
        "AV": 1,
        "Round": NaN,
        "Pick": NaN,
        "DrftYr": NaN,
        "Season": 2011,
        "Age": 22,
        "Team": "NOR",
        "G": 16,
        "GS": 1,
        "AV.1": 1,
        "Pos": "DB"
    },
    {
        "Rk": 223,
        "Player": "Danny Aiken",
        "AV": 1,
        "Round": NaN,
        "Pick": NaN,
        "DrftYr": NaN,
        "Season": 2011,
        "Age": 23,
        "Team": "NWE",
        "G": 16,
        "GS": 0,
        "AV.1": 1,
        "Pos": "LS"
    },
    {
        "Rk": 224,
        "Player": "Alex Albright",
        "AV": 1,
        "Round": NaN,
        "Pick": NaN,
        "DrftYr": NaN,
        "Season": 2011,
        "Age": 23,
        "Team": "DAL",
        "G": 16,
        "GS": 0,
        "AV.1": 1,
        "Pos": "LB"
    },
    {
        "Rk": 226,
        "Player": "Mister Alexander",
        "AV": 1,
        "Round": NaN,
        "Pick": NaN,
        "DrftYr": NaN,
        "Season": 2011,
        "Age": 23,
        "Team": "HOU",
        "G": 8,
        "GS": 0,
        "AV.1": 1,
        "Pos": "LB"
    },
    {
        "Rk": 233,
        "Player": "Colin Baxter",
        "AV": 1,
        "Round": NaN,
        "Pick": NaN,
        "DrftYr": NaN,
        "Season": 2011,
        "Age": 24,
        "Team": "NYJ,SDG",
        "G": 8,
        "GS": 2,
        "AV.1": 1,
        "Pos": "C"
    },
    {
        "Rk": 234,
        "Player": "Nick Bellore",
        "AV": 1,
        "Round": NaN,
        "Pick": NaN,
        "DrftYr": NaN,
        "Season": 2011,
        "Age": 22,
        "Team": "NYJ",
        "G": 16,
        "GS": 0,
        "AV.1": 1,
        "Pos": "LB"
    },
    {
        "Rk": 235,
        "Player": "Bront Bird",
        "AV": 1,
        "Round": NaN,
        "Pick": NaN,
        "DrftYr": NaN,
        "Season": 2011,
        "Age": 22,
        "Team": "SDG",
        "G": 9,
        "GS": 0,
        "AV.1": 1,
        "Pos": "LB"
    },
    {
        "Rk": 238,
        "Player": "Kyle Bosworth",
        "AV": 1,
        "Round": NaN,
        "Pick": NaN,
        "DrftYr": NaN,
        "Season": 2011,
        "Age": 25,
        "Team": "JAX",
        "G": 9,
        "GS": 0,
        "AV.1": 1,
        "Pos": "LB"
    },
    {
        "Rk": 241,
        "Player": "Cameron Bradfield",
        "AV": 1,
        "Round": NaN,
        "Pick": NaN,
        "DrftYr": NaN,
        "Season": 2011,
        "Age": 24,
        "Team": "JAX",
        "G": 10,
        "GS": 2,
        "AV.1": 1,
        "Pos": "T"
    },
    {
        "Rk": 244,
        "Player": "Patrick Brown",
        "AV": 1,
        "Round": NaN,
        "Pick": NaN,
        "DrftYr": NaN,
        "Season": 2011,
        "Age": 25,
        "Team": "MIN",
        "G": 16,
        "GS": 0,
        "AV.1": 1,
        "Pos": "T"
    },
    {
        "Rk": 253,
        "Player": "John Chick",
        "AV": 1,
        "Round": NaN,
        "Pick": NaN,
        "DrftYr": NaN,
        "Season": 2011,
        "Age": 29,
        "Team": "JAX",
        "G": 11,
        "GS": 0,
        "AV.1": 1,
        "Pos": "DE"
    },
    {
        "Rk": 257,
        "Player": "Jed Collins",
        "AV": 1,
        "Round": NaN,
        "Pick": NaN,
        "DrftYr": NaN,
        "Season": 2011,
        "Age": 25,
        "Team": "NOR",
        "G": 16,
        "GS": 11,
        "AV.1": 1,
        "Pos": "FB"
    },
    {
        "Rk": 258,
        "Player": "T.J. Conley",
        "AV": 1,
        "Round": NaN,
        "Pick": NaN,
        "DrftYr": NaN,
        "Season": 2011,
        "Age": 26,
        "Team": "NYJ",
        "G": 16,
        "GS": 0,
        "AV.1": 1,
        "Pos": "P"
    },
    {
        "Rk": 260,
        "Player": "Jim Cordle",
        "AV": 1,
        "Round": NaN,
        "Pick": NaN,
        "DrftYr": NaN,
        "Season": 2011,
        "Age": 24,
        "Team": "NYG",
        "G": 9,
        "GS": 0,
        "AV.1": 1,
        "Pos": "T"
    },
    {
        "Rk": 265,
        "Player": "Larry Dean",
        "AV": 1,
        "Round": NaN,
        "Pick": NaN,
        "DrftYr": NaN,
        "Season": 2011,
        "Age": 23,
        "Team": "MIN",
        "G": 16,
        "GS": 0,
        "AV.1": 1,
        "Pos": "LB"
    },
    {
        "Rk": 266,
        "Player": "Dom DeCicco",
        "AV": 1,
        "Round": NaN,
        "Pick": NaN,
        "DrftYr": NaN,
        "Season": 2011,
        "Age": 23,
        "Team": "CHI",
        "G": 16,
        "GS": 0,
        "AV.1": 1,
        "Pos": "LB"
    },
    {
        "Rk": 268,
        "Player": "Demarcus Dobbs",
        "AV": 1,
        "Round": NaN,
        "Pick": NaN,
        "DrftYr": NaN,
        "Season": 2011,
        "Age": 24,
        "Team": "SFO",
        "G": 12,
        "GS": 0,
        "AV.1": 1,
        "Pos": "DE"
    },
    {
        "Rk": 269,
        "Player": "James Dockery",
        "AV": 1,
        "Round": NaN,
        "Pick": NaN,
        "DrftYr": NaN,
        "Season": 2011,
        "Age": 23,
        "Team": "CLE",
        "G": 12,
        "GS": 0,
        "AV.1": 1,
        "Pos": "DB"
    },
    {
        "Rk": 270,
        "Player": "Ryan Donahue",
        "AV": 1,
        "Round": NaN,
        "Pick": NaN,
        "DrftYr": NaN,
        "Season": 2011,
        "Age": 23,
        "Team": "DET",
        "G": 8,
        "GS": 0,
        "AV.1": 1,
        "Pos": "P"
    },
    {
        "Rk": 273,
        "Player": "Auston English",
        "AV": 1,
        "Round": NaN,
        "Pick": NaN,
        "DrftYr": NaN,
        "Season": 2011,
        "Age": 24,
        "Team": "CLE",
        "G": 7,
        "GS": 0,
        "AV.1": 1,
        "Pos": "DE"
    },
    {
        "Rk": 282,
        "Player": "Chris Hawkins",
        "AV": 1,
        "Round": NaN,
        "Pick": NaN,
        "DrftYr": NaN,
        "Season": 2011,
        "Age": 25,
        "Team": "TEN",
        "G": 9,
        "GS": 0,
        "AV.1": 1,
        "Pos": "DB"
    },
    {
        "Rk": 283,
        "Player": "Chas Henry",
        "AV": 1,
        "Round": NaN,
        "Pick": NaN,
        "DrftYr": NaN,
        "Season": 2011,
        "Age": 22,
        "Team": "PHI",
        "G": 16,
        "GS": 0,
        "AV.1": 1,
        "Pos": "P"
    },
    {
        "Rk": 284,
        "Player": "Mark Herzlich",
        "AV": 1,
        "Round": NaN,
        "Pick": NaN,
        "DrftYr": NaN,
        "Season": 2011,
        "Age": 24,
        "Team": "NYG",
        "G": 11,
        "GS": 2,
        "AV.1": 1,
        "Pos": "LB"
    },
    {
        "Rk": 288,
        "Player": "Phillip Hunt",
        "AV": 1,
        "Round": NaN,
        "Pick": NaN,
        "DrftYr": NaN,
        "Season": 2011,
        "Age": 25,
        "Team": "PHI",
        "G": 9,
        "GS": 0,
        "AV.1": 1,
        "Pos": "DE"
    },
    {
        "Rk": 290,
        "Player": "Henry Hynoski",
        "AV": 1,
        "Round": NaN,
        "Pick": NaN,
        "DrftYr": NaN,
        "Season": 2011,
        "Age": 23,
        "Team": "NYG",
        "G": 11,
        "GS": 4,
        "AV.1": 1,
        "Pos": "RB"
    },
    {
        "Rk": 292,
        "Player": "M.D. Jennings",
        "AV": 1,
        "Round": NaN,
        "Pick": NaN,
        "DrftYr": NaN,
        "Season": 2011,
        "Age": 23,
        "Team": "GNB",
        "G": 15,
        "GS": 0,
        "AV.1": 1,
        "Pos": "DB"
    },
    {
        "Rk": 293,
        "Player": "Jeremiah Johnson",
        "AV": 1,
        "Round": NaN,
        "Pick": NaN,
        "DrftYr": NaN,
        "Season": 2011,
        "Age": 24,
        "Team": "DEN",
        "G": 8,
        "GS": 0,
        "AV.1": 1,
        "Pos": "RB"
    },
    {
        "Rk": 294,
        "Player": "Jeron Johnson",
        "AV": 1,
        "Round": NaN,
        "Pick": NaN,
        "DrftYr": NaN,
        "Season": 2011,
        "Age": 23,
        "Team": "SEA",
        "G": 8,
        "GS": 0,
        "AV.1": 1,
        "Pos": "DB"
    },
    {
        "Rk": 295,
        "Player": "Terrence Johnson",
        "AV": 1,
        "Round": NaN,
        "Pick": NaN,
        "DrftYr": NaN,
        "Season": 2011,
        "Age": 25,
        "Team": "IND",
        "G": 10,
        "GS": 2,
        "AV.1": 1,
        "Pos": "DB"
    },
    {
        "Rk": 296,
        "Player": "Tom Johnson",
        "AV": 1,
        "Round": NaN,
        "Pick": NaN,
        "DrftYr": NaN,
        "Season": 2011,
        "Age": 27,
        "Team": "NOR",
        "G": 13,
        "GS": 0,
        "AV.1": 1,
        "Pos": "DT"
    },
    {
        "Rk": 300,
        "Player": "Thomas Keiser",
        "AV": 1,
        "Round": NaN,
        "Pick": NaN,
        "DrftYr": NaN,
        "Season": 2011,
        "Age": 22,
        "Team": "CAR",
        "G": 8,
        "GS": 0,
        "AV.1": 1,
        "Pos": "LB"
    },
    {
        "Rk": 301,
        "Player": "Kevin Kowalski",
        "AV": 1,
        "Round": NaN,
        "Pick": NaN,
        "DrftYr": NaN,
        "Season": 2011,
        "Age": 22,
        "Team": "DAL",
        "G": 11,
        "GS": 0,
        "AV.1": 1,
        "Pos": "C"
    },
    {
        "Rk": 304,
        "Player": "Jamari Lattimore",
        "AV": 1,
        "Round": NaN,
        "Pick": NaN,
        "DrftYr": NaN,
        "Season": 2011,
        "Age": 23,
        "Team": "GNB",
        "G": 9,
        "GS": 0,
        "AV.1": 1,
        "Pos": "LB"
    },
    {
        "Rk": 308,
        "Player": "Ricardo Lockette",
        "AV": 1,
        "Round": NaN,
        "Pick": NaN,
        "DrftYr": NaN,
        "Season": 2011,
        "Age": 25,
        "Team": "SEA",
        "G": 2,
        "GS": 0,
        "AV.1": 1,
        "Pos": "WR"
    },
    {
        "Rk": 311,
        "Player": "Mossis Madu",
        "AV": 1,
        "Round": NaN,
        "Pick": NaN,
        "DrftYr": NaN,
        "Season": 2011,
        "Age": 24,
        "Team": "TAM",
        "G": 9,
        "GS": 0,
        "AV.1": 1,
        "Pos": "RB"
    },
    {
        "Rk": 312,
        "Player": "Steve Maneri",
        "AV": 1,
        "Round": NaN,
        "Pick": NaN,
        "DrftYr": NaN,
        "Season": 2011,
        "Age": 23,
        "Team": "KAN",
        "G": 6,
        "GS": 1,
        "AV.1": 1,
        "Pos": "T"
    },
    {
        "Rk": 317,
        "Player": "Nick McDonald",
        "AV": 1,
        "Round": NaN,
        "Pick": NaN,
        "DrftYr": NaN,
        "Season": 2011,
        "Age": 24,
        "Team": "NWE",
        "G": 4,
        "GS": 2,
        "AV.1": 1,
        "Pos": "G"
    },
    {
        "Rk": 319,
        "Player": "Jake McQuaide",
        "AV": 1,
        "Round": NaN,
        "Pick": NaN,
        "DrftYr": NaN,
        "Season": 2011,
        "Age": 24,
        "Team": "STL",
        "G": 16,
        "GS": 0,
        "AV.1": 1,
        "Pos": "LS"
    },
    {
        "Rk": 323,
        "Player": "Adrian Moten",
        "AV": 1,
        "Round": NaN,
        "Pick": NaN,
        "DrftYr": NaN,
        "Season": 2011,
        "Age": 23,
        "Team": "IND,SEA",
        "G": 12,
        "GS": 0,
        "AV.1": 1,
        "Pos": "LB"
    },
    {
        "Rk": 331,
        "Player": "Jermey Parnell",
        "AV": 1,
        "Round": NaN,
        "Pick": NaN,
        "DrftYr": NaN,
        "Season": 2011,
        "Age": 25,
        "Team": "DAL",
        "G": 6,
        "GS": 0,
        "AV.1": 1,
        "Pos": "T"
    },
    {
        "Rk": 334,
        "Player": "Spencer Paysinger",
        "AV": 1,
        "Round": NaN,
        "Pick": NaN,
        "DrftYr": NaN,
        "Season": 2011,
        "Age": 23,
        "Team": "NYG",
        "G": 15,
        "GS": 0,
        "AV.1": 1,
        "Pos": "LB"
    },
    {
        "Rk": 338,
        "Player": "Brandon Saine",
        "AV": 1,
        "Round": NaN,
        "Pick": NaN,
        "DrftYr": NaN,
        "Season": 2011,
        "Age": 23,
        "Team": "GNB",
        "G": 8,
        "GS": 0,
        "AV.1": 1,
        "Pos": "RB"
    },
    {
        "Rk": 343,
        "Player": "Willie Smith",
        "AV": 1,
        "Round": NaN,
        "Pick": NaN,
        "DrftYr": NaN,
        "Season": 2011,
        "Age": 25,
        "Team": "WAS",
        "G": 4,
        "GS": 3,
        "AV.1": 1,
        "Pos": "T"
    },
    {
        "Rk": 344,
        "Player": "Vic So'oto",
        "AV": 1,
        "Round": NaN,
        "Pick": NaN,
        "DrftYr": NaN,
        "Season": 2011,
        "Age": 24,
        "Team": "GNB",
        "G": 7,
        "GS": 0,
        "AV.1": 1,
        "Pos": "LB"
    },
    {
        "Rk": 345,
        "Player": "Quinton Spears",
        "AV": 1,
        "Round": NaN,
        "Pick": NaN,
        "DrftYr": NaN,
        "Season": 2011,
        "Age": 23,
        "Team": "CLE",
        "G": 13,
        "GS": 0,
        "AV.1": 1,
        "Pos": "LB"
    },
    {
        "Rk": 349,
        "Player": "Phillip Tanner",
        "AV": 1,
        "Round": NaN,
        "Pick": NaN,
        "DrftYr": NaN,
        "Season": 2011,
        "Age": 23,
        "Team": "DAL",
        "G": 9,
        "GS": 0,
        "AV.1": 1,
        "Pos": "RB"
    },
    {
        "Rk": 350,
        "Player": "Jeff Tarpinian",
        "AV": 1,
        "Round": NaN,
        "Pick": NaN,
        "DrftYr": NaN,
        "Season": 2011,
        "Age": 24,
        "Team": "NWE",
        "G": 7,
        "GS": 1,
        "AV.1": 1,
        "Pos": "LB"
    },
    {
        "Rk": 353,
        "Player": "Will Tukuafu",
        "AV": 1,
        "Round": NaN,
        "Pick": NaN,
        "DrftYr": NaN,
        "Season": 2011,
        "Age": 27,
        "Team": "SFO",
        "G": 4,
        "GS": 0,
        "AV.1": 1,
        "Pos": "DE"
    },
    {
        "Rk": 354,
        "Player": "Mitch Unrein",
        "AV": 1,
        "Round": NaN,
        "Pick": NaN,
        "DrftYr": NaN,
        "Season": 2011,
        "Age": 24,
        "Team": "DEN",
        "G": 14,
        "GS": 0,
        "AV.1": 1,
        "Pos": "DE"
    },
    {
        "Rk": 356,
        "Player": "Winston Venable",
        "AV": 1,
        "Round": NaN,
        "Pick": NaN,
        "DrftYr": NaN,
        "Season": 2011,
        "Age": 24,
        "Team": "CHI",
        "G": 12,
        "GS": 0,
        "AV.1": 1,
        "Pos": "DB"
    },
    {
        "Rk": 359,
        "Player": "Darrin Walls",
        "AV": 1,
        "Round": NaN,
        "Pick": NaN,
        "DrftYr": NaN,
        "Season": 2011,
        "Age": 23,
        "Team": "ATL",
        "G": 5,
        "GS": 0,
        "AV.1": 1,
        "Pos": "DB"
    },
    {
        "Rk": 363,
        "Player": "Chastin West",
        "AV": 1,
        "Round": NaN,
        "Pick": NaN,
        "DrftYr": NaN,
        "Season": 2011,
        "Age": 24,
        "Team": "JAX",
        "G": 12,
        "GS": 1,
        "AV.1": 1,
        "Pos": "WR"
    },
    {
        "Rk": 368,
        "Player": "Darvin Adams",
        "AV": 0,
        "Round": NaN,
        "Pick": NaN,
        "DrftYr": NaN,
        "Season": 2011,
        "Age": 21,
        "Team": "CAR",
        "G": 2,
        "GS": 0,
        "AV.1": 0,
        "Pos": "WR"
    },
    {
        "Rk": 369,
        "Player": "Kyle Adams",
        "AV": 0,
        "Round": NaN,
        "Pick": NaN,
        "DrftYr": NaN,
        "Season": 2011,
        "Age": 23,
        "Team": "CHI",
        "G": 8,
        "GS": 0,
        "AV.1": 0,
        "Pos": "TE"
    },
    {
        "Rk": 370,
        "Player": "Mario Addison",
        "AV": 0,
        "Round": NaN,
        "Pick": NaN,
        "DrftYr": NaN,
        "Season": 2011,
        "Age": 24,
        "Team": "CHI,IND",
        "G": 7,
        "GS": 0,
        "AV.1": 0,
        "Pos": "LB"
    },
    {
        "Rk": 371,
        "Player": "Kamar Aiken",
        "AV": 0,
        "Round": NaN,
        "Pick": NaN,
        "DrftYr": NaN,
        "Season": 2011,
        "Age": 22,
        "Team": "BUF",
        "G": 2,
        "GS": 0,
        "AV.1": 0,
        "Pos": "WR"
    },
    {
        "Rk": 373,
        "Player": "Armando Allen",
        "AV": 0,
        "Round": NaN,
        "Pick": NaN,
        "DrftYr": NaN,
        "Season": 2011,
        "Age": 22,
        "Team": "CHI",
        "G": 2,
        "GS": 0,
        "AV.1": 0,
        "Pos": "RB"
    },
    {
        "Rk": 375,
        "Player": "Emmanuel Arceneaux",
        "AV": 0,
        "Round": NaN,
        "Pick": NaN,
        "DrftYr": NaN,
        "Season": 2011,
        "Age": 24,
        "Team": "MIN",
        "G": 3,
        "GS": 0,
        "AV.1": 0,
        "Pos": "WR"
    },
    {
        "Rk": 376,
        "Player": "Tim Atchison",
        "AV": 0,
        "Round": NaN,
        "Pick": NaN,
        "DrftYr": NaN,
        "Season": 2011,
        "Age": 24,
        "Team": "STL",
        "G": 1,
        "GS": 0,
        "AV.1": 0,
        "Pos": "DB"
    },
    {
        "Rk": 377,
        "Player": "Thomas Austin",
        "AV": 0,
        "Round": NaN,
        "Pick": NaN,
        "DrftYr": NaN,
        "Season": 2011,
        "Age": 25,
        "Team": "HOU",
        "G": 3,
        "GS": 0,
        "AV.1": 0,
        "Pos": "G"
    },
    {
        "Rk": 379,
        "Player": "Josh Baker",
        "AV": 0,
        "Round": NaN,
        "Pick": NaN,
        "DrftYr": NaN,
        "Season": 2011,
        "Age": 25,
        "Team": "NYJ",
        "G": 11,
        "GS": 0,
        "AV.1": 0,
        "Pos": "TE"
    },
    {
        "Rk": 386,
        "Player": "Kevin Brock",
        "AV": 0,
        "Round": NaN,
        "Pick": NaN,
        "DrftYr": NaN,
        "Season": 2011,
        "Age": 25,
        "Team": "BUF",
        "G": 2,
        "GS": 0,
        "AV.1": 0,
        "Pos": "TE"
    },
    {
        "Rk": 387,
        "Player": "Richie Brockel",
        "AV": 0,
        "Round": NaN,
        "Pick": NaN,
        "DrftYr": NaN,
        "Season": 2011,
        "Age": 25,
        "Team": "CAR",
        "G": 11,
        "GS": 2,
        "AV.1": 0,
        "Pos": "TE"
    },
    {
        "Rk": 388,
        "Player": "Mason Brodine",
        "AV": 0,
        "Round": NaN,
        "Pick": NaN,
        "DrftYr": NaN,
        "Season": 2011,
        "Age": 23,
        "Team": "OAK",
        "G": 2,
        "GS": 0,
        "AV.1": 0,
        "Pos": "DE"
    },
    {
        "Rk": 389,
        "Player": "Bryant Browning",
        "AV": 0,
        "Round": NaN,
        "Pick": NaN,
        "DrftYr": NaN,
        "Season": 2011,
        "Age": 23,
        "Team": "CAR",
        "G": 1,
        "GS": 0,
        "AV.1": 0,
        "Pos": "G"
    },
    {
        "Rk": 392,
        "Player": "Corbin Bryant",
        "AV": 0,
        "Round": NaN,
        "Pick": NaN,
        "DrftYr": NaN,
        "Season": 2011,
        "Age": 23,
        "Team": "PIT",
        "G": 1,
        "GS": 0,
        "AV.1": 0,
        "Pos": "DT"
    },
    {
        "Rk": 394,
        "Player": "Rafael Bush",
        "AV": 0,
        "Round": NaN,
        "Pick": NaN,
        "DrftYr": NaN,
        "Season": 2011,
        "Age": 24,
        "Team": "DEN",
        "G": 6,
        "GS": 0,
        "AV.1": 0,
        "Pos": "DB"
    },
    {
        "Rk": 395,
        "Player": "Josh Bynes",
        "AV": 0,
        "Round": NaN,
        "Pick": NaN,
        "DrftYr": NaN,
        "Season": 2011,
        "Age": 22,
        "Team": "BAL",
        "G": 1,
        "GS": 0,
        "AV.1": 0,
        "Pos": "LB"
    },
    {
        "Rk": 396,
        "Player": "Rudy Carpenter",
        "AV": 0,
        "Round": NaN,
        "Pick": NaN,
        "DrftYr": NaN,
        "Season": 2011,
        "Age": 25,
        "Team": "TAM",
        "G": 1,
        "GS": 0,
        "AV.1": 0,
        "Pos": "QB"
    },
    {
        "Rk": 398,
        "Player": "Mike Caussin",
        "AV": 0,
        "Round": NaN,
        "Pick": NaN,
        "DrftYr": NaN,
        "Season": 2011,
        "Age": 24,
        "Team": "BUF",
        "G": 6,
        "GS": 2,
        "AV.1": 0,
        "Pos": "TE"
    },
    {
        "Rk": 399,
        "Player": "John Clay",
        "AV": 0,
        "Round": NaN,
        "Pick": NaN,
        "DrftYr": NaN,
        "Season": 2011,
        "Age": 23,
        "Team": "PIT",
        "G": 2,
        "GS": 0,
        "AV.1": 0,
        "Pos": "RB"
    },
    {
        "Rk": 401,
        "Player": "Tyler Clutts",
        "AV": 0,
        "Round": NaN,
        "Pick": NaN,
        "DrftYr": NaN,
        "Season": 2011,
        "Age": 27,
        "Team": "CHI",
        "G": 16,
        "GS": 8,
        "AV.1": 0,
        "Pos": "FB"
    },
    {
        "Rk": 402,
        "Player": "Colin Cochart",
        "AV": 0,
        "Round": NaN,
        "Pick": NaN,
        "DrftYr": NaN,
        "Season": 2011,
        "Age": 24,
        "Team": "CIN",
        "G": 10,
        "GS": 3,
        "AV.1": 0,
        "Pos": "TE"
    },
    {
        "Rk": 404,
        "Player": "Justin Cole",
        "AV": 0,
        "Round": NaN,
        "Pick": NaN,
        "DrftYr": NaN,
        "Season": 2011,
        "Age": 24,
        "Team": "STL",
        "G": 4,
        "GS": 0,
        "AV.1": 0,
        "Pos": "LB"
    },
    {
        "Rk": 405,
        "Player": "Kevin Cone",
        "AV": 0,
        "Round": NaN,
        "Pick": NaN,
        "DrftYr": NaN,
        "Season": 2011,
        "Age": 23,
        "Team": "ATL",
        "G": 1,
        "GS": 0,
        "AV.1": 0,
        "Pos": "WR"
    },
    {
        "Rk": 411,
        "Player": "Da'Mon Cromartie-Smith",
        "AV": 0,
        "Round": NaN,
        "Pick": NaN,
        "DrftYr": NaN,
        "Season": 2011,
        "Age": 24,
        "Team": "PIT",
        "G": 4,
        "GS": 0,
        "AV.1": 0,
        "Pos": "DB"
    },
    {
        "Rk": 417,
        "Player": "Shaun Draughn",
        "AV": 0,
        "Round": NaN,
        "Pick": NaN,
        "DrftYr": NaN,
        "Season": 2011,
        "Age": 24,
        "Team": "KAN",
        "G": 1,
        "GS": 0,
        "AV.1": 0,
        "Pos": "RB"
    },
    {
        "Rk": 418,
        "Player": "Robert Eddins",
        "AV": 0,
        "Round": NaN,
        "Pick": NaN,
        "DrftYr": NaN,
        "Season": 2011,
        "Age": 23,
        "Team": "BUF",
        "G": 1,
        "GS": 0,
        "AV.1": 0,
        "Pos": "LB"
    },
    {
        "Rk": 420,
        "Player": "John Estes",
        "AV": 0,
        "Round": NaN,
        "Pick": NaN,
        "DrftYr": NaN,
        "Season": 2011,
        "Age": 24,
        "Team": "JAX",
        "G": 2,
        "GS": 0,
        "AV.1": 0,
        "Pos": "C"
    },
    {
        "Rk": 421,
        "Player": "Darren Evans",
        "AV": 0,
        "Round": NaN,
        "Pick": NaN,
        "DrftYr": NaN,
        "Season": 2011,
        "Age": 23,
        "Team": "IND",
        "G": 2,
        "GS": 0,
        "AV.1": 0,
        "Pos": "RB"
    },
    {
        "Rk": 422,
        "Player": "Collin Franklin",
        "AV": 0,
        "Round": NaN,
        "Pick": NaN,
        "DrftYr": NaN,
        "Season": 2011,
        "Age": 23,
        "Team": "TAM",
        "G": 2,
        "GS": 0,
        "AV.1": 0,
        "Pos": "WR"
    },
    {
        "Rk": 423,
        "Player": "Stephen Franklin",
        "AV": 0,
        "Round": NaN,
        "Pick": NaN,
        "DrftYr": NaN,
        "Season": 2011,
        "Age": 23,
        "Team": "JAX",
        "G": 5,
        "GS": 0,
        "AV.1": 0,
        "Pos": "LB"
    },
    {
        "Rk": 424,
        "Player": "Darryl Gamble",
        "AV": 0,
        "Round": NaN,
        "Pick": NaN,
        "DrftYr": NaN,
        "Season": 2011,
        "Age": 24,
        "Team": "SDG",
        "G": 5,
        "GS": 0,
        "AV.1": 0,
        "Pos": "LB"
    },
    {
        "Rk": 425,
        "Player": "D'Andre Goodwin",
        "AV": 0,
        "Round": NaN,
        "Pick": NaN,
        "DrftYr": NaN,
        "Season": 2011,
        "Age": 24,
        "Team": "DEN",
        "G": 0,
        "GS": 0,
        "AV.1": 0,
        "Pos": "WR"
    },
    {
        "Rk": 427,
        "Player": "Marshay Green",
        "AV": 0,
        "Round": NaN,
        "Pick": NaN,
        "DrftYr": NaN,
        "Season": 2011,
        "Age": 25,
        "Team": "ARI",
        "G": 1,
        "GS": 0,
        "AV.1": 0,
        "Pos": "DB"
    },
    {
        "Rk": 432,
        "Player": "DuJuan Harris",
        "AV": 0,
        "Round": NaN,
        "Pick": NaN,
        "DrftYr": NaN,
        "Season": 2011,
        "Age": 23,
        "Team": "JAX",
        "G": 5,
        "GS": 0,
        "AV.1": 0,
        "Pos": "RB"
    },
    {
        "Rk": 433,
        "Player": "Joe Hastings",
        "AV": 0,
        "Round": NaN,
        "Pick": NaN,
        "DrftYr": NaN,
        "Season": 2011,
        "Age": 24,
        "Team": "SFO",
        "G": 1,
        "GS": 0,
        "AV.1": 0,
        "Pos": "WR"
    },
    {
        "Rk": 434,
        "Player": "T.J. Heath",
        "AV": 0,
        "Round": NaN,
        "Pick": NaN,
        "DrftYr": NaN,
        "Season": 2011,
        "Age": 24,
        "Team": "JAX",
        "G": 5,
        "GS": 0,
        "AV.1": 0,
        "Pos": "DB"
    },
    {
        "Rk": 436,
        "Player": "Dwayne Hendricks",
        "AV": 0,
        "Round": NaN,
        "Pick": NaN,
        "DrftYr": NaN,
        "Season": 2011,
        "Age": 25,
        "Team": "NYG",
        "G": 1,
        "GS": 0,
        "AV.1": 0,
        "Pos": "DT"
    },
    {
        "Rk": 437,
        "Player": "Ricky Henry",
        "AV": 0,
        "Round": NaN,
        "Pick": NaN,
        "DrftYr": NaN,
        "Season": 2011,
        "Age": 24,
        "Team": "CHI",
        "G": 1,
        "GS": 0,
        "AV.1": 0,
        "Pos": "G"
    },
    {
        "Rk": 438,
        "Player": "Michael Higgins",
        "AV": 0,
        "Round": NaN,
        "Pick": NaN,
        "DrftYr": NaN,
        "Season": 2011,
        "Age": 24,
        "Team": "NOR",
        "G": 2,
        "GS": 0,
        "AV.1": 0,
        "Pos": "TE"
    },
    {
        "Rk": 440,
        "Player": "Devin Holland",
        "AV": 0,
        "Round": NaN,
        "Pick": NaN,
        "DrftYr": NaN,
        "Season": 2011,
        "Age": 23,
        "Team": "TAM",
        "G": 4,
        "GS": 0,
        "AV.1": 0,
        "Pos": "DB"
    },
    {
        "Rk": 443,
        "Player": "Kevin Hughes",
        "AV": 0,
        "Round": NaN,
        "Pick": NaN,
        "DrftYr": NaN,
        "Season": 2011,
        "Age": 23,
        "Team": "STL",
        "G": 3,
        "GS": 0,
        "AV.1": 0,
        "Pos": "T"
    },
    {
        "Rk": 444,
        "Player": "Mortty Ivy",
        "AV": 0,
        "Round": NaN,
        "Pick": NaN,
        "DrftYr": NaN,
        "Season": 2011,
        "Age": 25,
        "Team": "PIT",
        "G": 6,
        "GS": 0,
        "AV.1": 0,
        "Pos": "LB"
    },
    {
        "Rk": 447,
        "Player": "Ben Jacobs",
        "AV": 0,
        "Round": NaN,
        "Pick": NaN,
        "DrftYr": NaN,
        "Season": 2011,
        "Age": 23,
        "Team": "CLE",
        "G": 5,
        "GS": 0,
        "AV.1": 0,
        "Pos": "LB"
    },
    {
        "Rk": 448,
        "Player": "George Johnson",
        "AV": 0,
        "Round": NaN,
        "Pick": NaN,
        "DrftYr": NaN,
        "Season": 2011,
        "Age": 24,
        "Team": "TAM",
        "G": 4,
        "GS": 0,
        "AV.1": 0,
        "Pos": "DE"
    },
    {
        "Rk": 449,
        "Player": "Chris Jones",
        "AV": 0,
        "Round": NaN,
        "Pick": NaN,
        "DrftYr": NaN,
        "Season": 2011,
        "Age": 22,
        "Team": "DAL",
        "G": 2,
        "GS": 0,
        "AV.1": 0,
        "Pos": "P"
    },
    {
        "Rk": 450,
        "Player": "Eddie Jones",
        "AV": 0,
        "Round": NaN,
        "Pick": NaN,
        "DrftYr": NaN,
        "Season": 2011,
        "Age": 23,
        "Team": "NYJ",
        "G": 1,
        "GS": 0,
        "AV.1": 0,
        "Pos": "DT"
    },
    {
        "Rk": 452,
        "Player": "Jarriel King",
        "AV": 0,
        "Round": NaN,
        "Pick": NaN,
        "DrftYr": NaN,
        "Season": 2011,
        "Age": 24,
        "Team": "SEA",
        "G": 1,
        "GS": 0,
        "AV.1": 0,
        "Pos": "T"
    },
    {
        "Rk": 456,
        "Player": "Michael Lockley",
        "AV": 0,
        "Round": NaN,
        "Pick": NaN,
        "DrftYr": NaN,
        "Season": 2011,
        "Age": 23,
        "Team": "JAX",
        "G": 7,
        "GS": 0,
        "AV.1": 0,
        "Pos": "LB"
    },
    {
        "Rk": 458,
        "Player": "Scott Lutrus",
        "AV": 0,
        "Round": NaN,
        "Pick": NaN,
        "DrftYr": NaN,
        "Season": 2011,
        "Age": 23,
        "Team": "IND",
        "G": 4,
        "GS": 0,
        "AV.1": 0,
        "Pos": "LB"
    },
    {
        "Rk": 460,
        "Player": "Jeff Maehl",
        "AV": 0,
        "Round": NaN,
        "Pick": NaN,
        "DrftYr": NaN,
        "Season": 2011,
        "Age": 22,
        "Team": "HOU",
        "G": 3,
        "GS": 0,
        "AV.1": 0,
        "Pos": "WR"
    },
    {
        "Rk": 461,
        "Player": "Ryan Mahaffey",
        "AV": 0,
        "Round": NaN,
        "Pick": NaN,
        "DrftYr": NaN,
        "Season": 2011,
        "Age": 24,
        "Team": "IND",
        "G": 5,
        "GS": 0,
        "AV.1": 0,
        "Pos": "RB"
    },
    {
        "Rk": 462,
        "Player": "Kevin Malast",
        "AV": 0,
        "Round": NaN,
        "Pick": NaN,
        "DrftYr": NaN,
        "Season": 2011,
        "Age": 25,
        "Team": "TEN",
        "G": 3,
        "GS": 0,
        "AV.1": 0,
        "Pos": "LB"
    },
    {
        "Rk": 467,
        "Player": "Richmond McGee",
        "AV": 0,
        "Round": NaN,
        "Pick": NaN,
        "DrftYr": NaN,
        "Season": 2011,
        "Age": 28,
        "Team": "CLE",
        "G": 1,
        "GS": 0,
        "AV.1": 0,
        "Pos": "P"
    },
    {
        "Rk": 469,
        "Player": "Mike McNeill",
        "AV": 0,
        "Round": NaN,
        "Pick": NaN,
        "DrftYr": NaN,
        "Season": 2011,
        "Age": 23,
        "Team": "IND",
        "G": 4,
        "GS": 0,
        "AV.1": 0,
        "Pos": "TE"
    },
    {
        "Rk": 470,
        "Player": "Richard Medlin",
        "AV": 0,
        "Round": NaN,
        "Pick": NaN,
        "DrftYr": NaN,
        "Season": 2011,
        "Age": 24,
        "Team": "MIA",
        "G": 1,
        "GS": 0,
        "AV.1": 0,
        "Pos": "RB"
    },
    {
        "Rk": 471,
        "Player": "Drew Miller",
        "AV": 0,
        "Round": NaN,
        "Pick": NaN,
        "DrftYr": NaN,
        "Season": 2011,
        "Age": 26,
        "Team": "STL",
        "G": 1,
        "GS": 0,
        "AV.1": 0,
        "Pos": "C"
    },
    {
        "Rk": 473,
        "Player": "Mike Morgan",
        "AV": 0,
        "Round": NaN,
        "Pick": NaN,
        "DrftYr": NaN,
        "Season": 2011,
        "Age": 23,
        "Team": "SEA",
        "G": 5,
        "GS": 0,
        "AV.1": 0,
        "Pos": "LB"
    },
    {
        "Rk": 476,
        "Player": "Rob Myers",
        "AV": 0,
        "Round": NaN,
        "Pick": NaN,
        "DrftYr": NaN,
        "Season": 2011,
        "Age": 25,
        "Team": "WAS",
        "G": 1,
        "GS": 0,
        "AV.1": 0,
        "Pos": "TE"
    },
    {
        "Rk": 480,
        "Player": "Jamar Newsome",
        "AV": 0,
        "Round": NaN,
        "Pick": NaN,
        "DrftYr": NaN,
        "Season": 2011,
        "Age": 24,
        "Team": "JAX",
        "G": 2,
        "GS": 0,
        "AV.1": 0,
        "Pos": "WR"
    },
    {
        "Rk": 484,
        "Player": "Ron Parker",
        "AV": 0,
        "Round": NaN,
        "Pick": NaN,
        "DrftYr": NaN,
        "Season": 2011,
        "Age": 24,
        "Team": "OAK,SEA",
        "G": 5,
        "GS": 0,
        "AV.1": 0,
        "Pos": "DB"
    },
    {
        "Rk": 485,
        "Player": "Zack Pianalto",
        "AV": 0,
        "Round": NaN,
        "Pick": NaN,
        "DrftYr": NaN,
        "Season": 2011,
        "Age": 22,
        "Team": "TAM",
        "G": 13,
        "GS": 0,
        "AV.1": 0,
        "Pos": "TE"
    },
    {
        "Rk": 487,
        "Player": "Quinn Porter",
        "AV": 0,
        "Round": NaN,
        "Pick": NaN,
        "DrftYr": NaN,
        "Season": 2011,
        "Age": 25,
        "Team": "STL",
        "G": 12,
        "GS": 0,
        "AV.1": 0,
        "Pos": "RB"
    },
    {
        "Rk": 490,
        "Player": "Julius Pruitt",
        "AV": 0,
        "Round": NaN,
        "Pick": NaN,
        "DrftYr": NaN,
        "Season": 2011,
        "Age": 26,
        "Team": "MIA",
        "G": 9,
        "GS": 0,
        "AV.1": 0,
        "Pos": "WR"
    },
    {
        "Rk": 491,
        "Player": "Allen Reisner",
        "AV": 0,
        "Round": NaN,
        "Pick": NaN,
        "DrftYr": NaN,
        "Season": 2011,
        "Age": 23,
        "Team": "MIN",
        "G": 6,
        "GS": 0,
        "AV.1": 0,
        "Pos": "TE"
    },
    {
        "Rk": 492,
        "Player": "Eron Riley",
        "AV": 0,
        "Round": NaN,
        "Pick": NaN,
        "DrftYr": NaN,
        "Season": 2011,
        "Age": 24,
        "Team": "NYJ",
        "G": 1,
        "GS": 0,
        "AV.1": 0,
        "Pos": "WR"
    },
    {
        "Rk": 494,
        "Player": "Brian Sanford",
        "AV": 0,
        "Round": NaN,
        "Pick": NaN,
        "DrftYr": NaN,
        "Season": 2011,
        "Age": 24,
        "Team": "CLE",
        "G": 5,
        "GS": 0,
        "AV.1": 0,
        "Pos": "DT"
    },
    {
        "Rk": 495,
        "Player": "Weslye Saunders",
        "AV": 0,
        "Round": NaN,
        "Pick": NaN,
        "DrftYr": NaN,
        "Season": 2011,
        "Age": 22,
        "Team": "PIT",
        "G": 16,
        "GS": 6,
        "AV.1": 0,
        "Pos": "WR"
    },
    {
        "Rk": 498,
        "Player": "Alex Silvestro",
        "AV": 0,
        "Round": NaN,
        "Pick": NaN,
        "DrftYr": NaN,
        "Season": 2011,
        "Age": 23,
        "Team": "NWE",
        "G": 1,
        "GS": 0,
        "AV.1": 0,
        "Pos": "DE"
    },
    {
        "Rk": 499,
        "Player": "Mana Silva",
        "AV": 0,
        "Round": NaN,
        "Pick": NaN,
        "DrftYr": NaN,
        "Season": 2011,
        "Age": 23,
        "Team": "DAL",
        "G": 2,
        "GS": 0,
        "AV.1": 0,
        "Pos": "DB"
    },
    {
        "Rk": 500,
        "Player": "Ricardo Silva",
        "AV": 0,
        "Round": NaN,
        "Pick": NaN,
        "DrftYr": NaN,
        "Season": 2011,
        "Age": 23,
        "Team": "DET",
        "G": 4,
        "GS": 0,
        "AV.1": 0,
        "Pos": "DB"
    },
    {
        "Rk": 502,
        "Player": "Armond Smith",
        "AV": 0,
        "Round": NaN,
        "Pick": NaN,
        "DrftYr": NaN,
        "Season": 2011,
        "Age": 25,
        "Team": "CLE",
        "G": 3,
        "GS": 0,
        "AV.1": 0,
        "Pos": "RB"
    },
    {
        "Rk": 503,
        "Player": "Brian Smith",
        "AV": 0,
        "Round": NaN,
        "Pick": NaN,
        "DrftYr": NaN,
        "Season": 2011,
        "Age": 22,
        "Team": "CLE",
        "G": 2,
        "GS": 0,
        "AV.1": 0,
        "Pos": "LB"
    },
    {
        "Rk": 504,
        "Player": "Chris Smith",
        "AV": 0,
        "Round": NaN,
        "Pick": NaN,
        "DrftYr": NaN,
        "Season": 2011,
        "Age": 24,
        "Team": "STL",
        "G": 3,
        "GS": 0,
        "AV.1": 0,
        "Pos": "DB"
    },
    {
        "Rk": 507,
        "Player": "Chad Spann",
        "AV": 0,
        "Round": NaN,
        "Pick": NaN,
        "DrftYr": NaN,
        "Season": 2011,
        "Age": 23,
        "Team": "PIT",
        "G": 0,
        "GS": 0,
        "AV.1": 0,
        "Pos": "RB"
    },
    {
        "Rk": 510,
        "Player": "Ronald Talley",
        "AV": 0,
        "Round": NaN,
        "Pick": NaN,
        "DrftYr": NaN,
        "Season": 2011,
        "Age": 25,
        "Team": "ARI",
        "G": 6,
        "GS": 0,
        "AV.1": 0,
        "Pos": "DE"
    },
    {
        "Rk": 511,
        "Player": "Martin Tevaseu",
        "AV": 0,
        "Round": NaN,
        "Pick": NaN,
        "DrftYr": NaN,
        "Season": 2011,
        "Age": 24,
        "Team": "NYJ",
        "G": 5,
        "GS": 0,
        "AV.1": 0,
        "Pos": "DT"
    },
    {
        "Rk": 512,
        "Player": "Manase Tonga",
        "AV": 0,
        "Round": NaN,
        "Pick": NaN,
        "DrftYr": NaN,
        "Season": 2011,
        "Age": 27,
        "Team": "OAK",
        "G": 11,
        "GS": 3,
        "AV.1": 0,
        "Pos": "RB"
    },
    {
        "Rk": 513,
        "Player": "Patrick Trahan",
        "AV": 0,
        "Round": NaN,
        "Pick": NaN,
        "DrftYr": NaN,
        "Season": 2011,
        "Age": 25,
        "Team": "CHI",
        "G": 5,
        "GS": 0,
        "AV.1": 0,
        "Pos": "LB"
    },
    {
        "Rk": 514,
        "Player": "Justin Trattou",
        "AV": 0,
        "Round": NaN,
        "Pick": NaN,
        "DrftYr": NaN,
        "Season": 2011,
        "Age": 23,
        "Team": "NYG",
        "G": 6,
        "GS": 0,
        "AV.1": 0,
        "Pos": "DE"
    },
    {
        "Rk": 515,
        "Player": "Kiante Tripp",
        "AV": 0,
        "Round": NaN,
        "Pick": NaN,
        "DrftYr": NaN,
        "Season": 2011,
        "Age": 24,
        "Team": "CLE",
        "G": 3,
        "GS": 0,
        "AV.1": 0,
        "Pos": "DT"
    },
    {
        "Rk": 519,
        "Player": "Ross Ventrone",
        "AV": 0,
        "Round": NaN,
        "Pick": NaN,
        "DrftYr": NaN,
        "Season": 2011,
        "Age": 25,
        "Team": "NWE",
        "G": 8,
        "GS": 0,
        "AV.1": 0,
        "Pos": "DB"
    },
    {
        "Rk": 523,
        "Player": "Anthony Walters",
        "AV": 0,
        "Round": NaN,
        "Pick": NaN,
        "DrftYr": NaN,
        "Season": 2011,
        "Age": 23,
        "Team": "CHI",
        "G": 4,
        "GS": 0,
        "AV.1": 0,
        "Pos": "DB"
    },
    {
        "Rk": 524,
        "Player": "Bryan Walters",
        "AV": 0,
        "Round": NaN,
        "Pick": NaN,
        "DrftYr": NaN,
        "Season": 2011,
        "Age": 24,
        "Team": "SDG",
        "G": 4,
        "GS": 0,
        "AV.1": 0,
        "Pos": "WR"
    },
    {
        "Rk": 526,
        "Player": "Chavis Williams",
        "AV": 0,
        "Round": NaN,
        "Pick": NaN,
        "DrftYr": NaN,
        "Season": 2011,
        "Age": 22,
        "Team": "BAL",
        "G": 5,
        "GS": 0,
        "AV.1": 0,
        "Pos": "LB"
    },
    {
        "Rk": 527,
        "Player": "Ian Williams",
        "AV": 0,
        "Round": NaN,
        "Pick": NaN,
        "DrftYr": NaN,
        "Season": 2011,
        "Age": 22,
        "Team": "SFO",
        "G": 1,
        "GS": 0,
        "AV.1": 0,
        "Pos": "DT"
    },
    {
        "Rk": 528,
        "Player": "LaQuan Williams",
        "AV": 0,
        "Round": NaN,
        "Pick": NaN,
        "DrftYr": NaN,
        "Season": 2011,
        "Age": 23,
        "Team": "BAL",
        "G": 12,
        "GS": 0,
        "AV.1": 0,
        "Pos": "WR"
    },
    {
        "Rk": 531,
        "Player": "Tracy Wilson",
        "AV": 0,
        "Round": NaN,
        "Pick": NaN,
        "DrftYr": NaN,
        "Season": 2011,
        "Age": 22,
        "Team": "NYJ",
        "G": 5,
        "GS": 0,
        "AV.1": 0,
        "Pos": "DB"
    },
    {
        "Rk": 533,
        "Player": "Will Yeatman",
        "AV": 0,
        "Round": NaN,
        "Pick": NaN,
        "DrftYr": NaN,
        "Season": 2011,
        "Age": 23,
        "Team": "MIA",
        "G": 3,
        "GS": 2,
        "AV.1": 0,
        "Pos": "TE"
    },
    {
        "Rk": 534,
        "Player": "Christian Yount",
        "AV": 0,
        "Round": NaN,
        "Pick": NaN,
        "DrftYr": NaN,
        "Season": 2011,
        "Age": 23,
        "Team": "CLE,TAM",
        "G": 12,
        "GS": 0,
        "AV.1": 0,
        "Pos": "C"
    }
]